pyCompute/KernelOperations.py
pyCompute/__init__.py
pyCompute/error.py
pyCompute/graph.py
pyCompute/algorithms/__init__.py
pyCompute/algorithms/dfs.py
pyCompute/algorithms/postorder.py
pyCompute/algorithms/postorder_v2.py
pyCompute/runtime/__init__.py
pyCompute/runtime/domain_decomposition.py
pyCompute/runtime/session.py
pyCompute/runtime/session_2x.py
pyCompute/runtime/string_session.py
pyCompute/text_processing/StringOperations.py
pyCompute/text_processing/__init__.py
pyCompute/text_processing/graph.py
pycompute-1.0.dist-info/METADATA
pycompute-1.0.dist-info/RECORD
pycompute-1.0.dist-info/WHEEL
pycompute-1.0.dist-info/top_level.txt
