Metadata-Version: 2.1
Name: pycompute
Version: 1.0
Summary: A computation graph library with support for parallelism , numerical and string computations.
Home-page: https://github.com/Narasimha1997/bzCompute
Author: Narasimha Prasanna HN
Author-email: narasimhaprasannahn@gmail.com
License: UNKNOWN
Platform: UNKNOWN
Classifier: Programming Language :: Python :: 3
Classifier: License :: OSI Approved :: MIT License
Classifier: Operating System :: OS Independent
